nenupytf/__init__.py
nenupytf/metadata.py
nenupytf/display/__init__.py
nenupytf/display/plot.py
nenupytf/other/__init__.py
nenupytf/other/bandpass_coeffs.dat
nenupytf/other/const.py
nenupytf/other/tools.py
nenupytf/process/__init__.py
nenupytf/process/analysis.py
nenupytf/process/fits_conversion.py
nenupytf/read/__init__.py
nenupytf/read/lane.py
nenupytf/read/obsrepo.py
nenupytf/read/spectrum.py
nenupytf/stokes/__init__.py
nenupytf/stokes/specdata.py
nenupytf/stokes/stokes.py
nenupytf-0.1.0.data/scripts/nenupytf-info
nenupytf-0.1.0.data/scripts/nenupytf-plot
nenupytf-0.1.0.dist-info/LICENSE
nenupytf-0.1.0.dist-info/METADATA
nenupytf-0.1.0.dist-info/WHEEL
nenupytf-0.1.0.dist-info/top_level.txt
nenupytf-0.1.0.dist-info/RECORD
