Metadata-Version: 2.1
Name: nenupytf
Version: 0.1.0
Summary: NenuFAR Python package
Home-page: https://github.com/AlanLoh/nenupy-tf.git
Author: Alan Loh
Author-email: alan.loh@obspm.fr
License: MIT
Platform: UNKNOWN
Requires-Python: >=3.5
Requires-Dist: numpy
Requires-Dist: astropy
Requires-Dist: psutil
